<lircremotes creation-date="Wed Jul 22 23:04:09 2015" creator="" lircversion="0.8.6" lirc2xml_version="0.1.2" configfile="remotes/motorola/VIP_1510.lircd.conf" decodeir_version="2.40">
  <remote name="Motorola_VIP1510">
    <lircdata type="RC5" bits="16" flags="2" eps="30" aeps="100" pthree="0" sthree="0" ptwo="0" stwo="0" pone="320" sone="320" pzero="320" szero="320" plead="640" ptrail="0" pfoot="0" sfoot="0" prepeat="0" srepeat="0" pre_data_bits="16" pre_data="61439" post_data_bits="0" post_data="0" pre_p="0" pre_s="0" post_p="0" post_s="0" gap="74500" gap2="0" repeat_gap="0" toggle_bit="0" toggle_bit_mask="0" min_repeat="0" min_code_repeat="0" freq="56400" duty_cycle="33" toggle_mask="0" rc6_mask="0" baud="0" bits_in_byte="0" parity="0" stop_bits="0" ignore_mask="0"/>
    <code name="KEY_1" codeno="0x000000000000A6F0">
      <ccf>0000 0049 001d 0000 0093 006b 0024 0012 0012 0012 0012 0012 0024 0024 0012 0012 0012 0012 0012 0012 0012 0012 0012 0012 0012 0012 0012 0012 0012 0012 0012 0012 0012 0012 0012 0012 0012 0012 0024 0024 0024 0012 0012 0024 0012 0012 0024 0024 0012 0012 0012 0012 0012 0012 0024 0012 0012 0012 0012 0012 0012 106a</ccf>
    </code>
    <code name="KEY_2" codeno="0x00000000000096FF">
      <ccf>0000 0049 001e 0000 0093 006b 0024 0012 0012 0012 0012 0012 0024 0024 0012 0012 0012 0012 0012 0012 0012 0012 0012 0012 0012 0012 0012 0012 0012 0012 0012 0012 0012 0012 0012 0012 0012 0012 0024 0012 0012 0024 0024 0024 0012 0012 0024 0024 0012 0012 0012 0012 0012 0012 0012 0012 0012 0012 0012 0012 0012 0012 0012 106a</ccf>
    </code>
    <code name="KEY_3" codeno="0x00000000000086FE">
      <ccf>0000 0049 001e 0000 0093 006b 0024 0012 0012 0012 0012 0012 0024 0024 0012 0012 0012 0012 0012 0012 0012 0012 0012 0012 0012 0012 0012 0012 0012 0012 0012 0012 0012 0012 0012 0012 0012 0012 0024 0012 0012 0012 0012 0012 0012 0024 0012 0012 0024 0024 0012 0012 0012 0012 0012 0012 0012 0012 0012 0012 0012 0012 0024 106a</ccf>
    </code>
    <code name="KEY_4" codeno="0x000000000000E3F1">
      <ccf>0000 0049 001f 0000 0093 006b 0024 0012 0012 0012 0012 0012 0024 0024 0012 0012 0012 0012 0012 0012 0012 0012 0012 0012 0012 0012 0012 0012 0012 0012 0012 0012 0012 0012 0012 0012 0012 0012 0012 0012 0012 0012 0024 0012 0012 0012 0012 0024 0012 0012 0012 0012 0012 0012 0012 0012 0012 0012 0024 0012 0012 0012 0012 0024 0012 106a</ccf>
    </code>
    <code name="KEY_5" codeno="0x000000000000D3F0">
      <ccf>0000 0049 001e 0000 0093 006b 0024 0012 0012 0012 0012 0012 0024 0024 0012 0012 0012 0012 0012 0012 0012 0012 0012 0012 0012 0012 0012 0012 0012 0012 0012 0012 0012 0012 0012 0012 0012 0012 0012 0012 0024 0024 0024 0012 0012 0024 0012 0012 0012 0012 0012 0012 0012 0012 0012 0012 0024 0012 0012 0012 0012 0012 0012 106a</ccf>
    </code>
    <code name="KEY_6" codeno="0x000000000000C3FF">
      <ccf>0000 0049 0020 0000 0093 006b 0024 0012 0012 0012 0012 0012 0024 0024 0012 0012 0012 0012 0012 0012 0012 0012 0012 0012 0012 0012 0012 0012 0012 0012 0012 0012 0012 0012 0012 0012 0012 0012 0012 0012 0024 0012 0012 0012 0012 0012 0012 0024 0012 0012 0012 0012 0012 0012 0012 0012 0012 0012 0012 0012 0012 0012 0012 0012 0012 0012 0012 106a</ccf>
    </code>
    <code name="KEY_7" codeno="0x000000000000B3FE">
      <ccf>0000 0049 001e 0000 0093 006b 0024 0012 0012 0012 0012 0012 0024 0024 0012 0012 0012 0012 0012 0012 0012 0012 0012 0012 0012 0012 0012 0012 0012 0012 0012 0012 0012 0012 0012 0012 0012 0012 0024 0024 0012 0012 0024 0012 0012 0024 0012 0012 0012 0012 0012 0012 0012 0012 0012 0012 0012 0012 0012 0012 0012 0012 0024 106a</ccf>
    </code>
    <code name="KEY_8" codeno="0x000000000000A3FD">
      <ccf>0000 0049 001e 0000 0093 006b 0024 0012 0012 0012 0012 0012 0024 0024 0012 0012 0012 0012 0012 0012 0012 0012 0012 0012 0012 0012 0012 0012 0012 0012 0012 0012 0012 0012 0012 0012 0012 0012 0024 0024 0024 0012 0012 0012 0012 0024 0012 0012 0012 0012 0012 0012 0012 0012 0012 0012 0012 0012 0012 0012 0024 0024 0012 106a</ccf>
    </code>
    <code name="KEY_9" codeno="0x00000000000093FC">
      <ccf>0000 0049 001e 0000 0093 006b 0024 0012 0012 0012 0012 0012 0024 0024 0012 0012 0012 0012 0012 0012 0012 0012 0012 0012 0012 0012 0012 0012 0012 0012 0012 0012 0012 0012 0012 0012 0012 0012 0024 0012 0012 0024 0024 0012 0012 0024 0012 0012 0012 0012 0012 0012 0012 0012 0012 0012 0012 0012 0012 0012 0024 0012 0012 106a</ccf>
    </code>
    <code name="KEY_0" codeno="0x000000000000E2F0">
      <ccf>0000 0049 001e 0000 0093 006b 0024 0012 0012 0012 0012 0012 0024 0024 0012 0012 0012 0012 0012 0012 0012 0012 0012 0012 0012 0012 0012 0012 0012 0012 0012 0012 0012 0012 0012 0012 0012 0012 0012 0012 0012 0012 0024 0012 0012 0012 0012 0024 0024 0024 0012 0012 0012 0012 0012 0012 0024 0012 0012 0012 0012 0012 0012 106a</ccf>
    </code>
    <code name="KEY_MUTE" codeno="0x00000000000094FD">
      <ccf>0000 0049 001d 0000 0093 006b 0024 0012 0012 0012 0012 0012 0024 0024 0012 0012 0012 0012 0012 0012 0012 0012 0012 0012 0012 0012 0012 0012 0012 0012 0012 0012 0012 0012 0012 0012 0012 0012 0024 0012 0012 0024 0024 0024 0024 0012 0012 0024 0012 0012 0012 0012 0012 0012 0012 0012 0012 0012 0024 0024 0012 106a</ccf>
    </code>
    <code name="KEY_TEXT" codeno="0x000000000000D4F1">
      <ccf>0000 0049 001d 0000 0093 006b 0024 0012 0012 0012 0012 0012 0024 0024 0012 0012 0012 0012 0012 0012 0012 0012 0012 0012 0012 0012 0012 0012 0012 0012 0012 0012 0012 0012 0012 0012 0012 0012 0012 0012 0024 0024 0024 0024 0024 0012 0012 0024 0012 0012 0012 0012 0012 0012 0024 0012 0012 0012 0012 0024 0012 106a</ccf>
    </code>
    <code name="KEY_TV" codeno="0x000000000000E6F4">
      <ccf>0000 0049 001d 0000 0093 006b 0024 0012 0012 0012 0012 0012 0024 0024 0012 0012 0012 0012 0012 0012 0012 0012 0012 0012 0012 0012 0012 0012 0012 0012 0012 0012 0012 0012 0012 0012 0012 0012 0012 0012 0012 0012 0024 0012 0012 0024 0012 0012 0024 0024 0012 0012 0012 0012 0012 0012 0024 0024 0024 0012 0012 106a</ccf>
    </code>
    <code name="circle" codeno="0x000000000000D0FD">
      <ccf>0000 0049 001e 0000 0093 006b 0024 0012 0012 0012 0012 0012 0024 0024 0012 0012 0012 0012 0012 0012 0012 0012 0012 0012 0012 0012 0012 0012 0012 0012 0012 0012 0012 0012 0012 0012 0012 0012 0012 0012 0024 0024 0024 0012 0012 0012 0012 0012 0012 0024 0012 0012 0012 0012 0012 0012 0012 0012 0012 0012 0024 0024 0012 106a</ccf>
    </code>
    <code name="KEY_WWW" codeno="0x000000000000A2FC">
      <ccf>0000 0049 001d 0000 0093 006b 0024 0012 0012 0012 0012 0012 0024 0024 0012 0012 0012 0012 0012 0012 0012 0012 0012 0012 0012 0012 0012 0012 0012 0012 0012 0012 0012 0012 0012 0012 0012 0012 0024 0024 0024 0012 0012 0012 0012 0024 0024 0024 0012 0012 0012 0012 0012 0012 0012 0012 0012 0012 0024 0012 0012 106a</ccf>
    </code>
    <code name="KEY_UP" codeno="0x000000000000C7F3">
      <ccf>0000 0049 001f 0000 0093 006b 0024 0012 0012 0012 0012 0012 0024 0024 0012 0012 0012 0012 0012 0012 0012 0012 0012 0012 0012 0012 0012 0012 0012 0012 0012 0012 0012 0012 0012 0012 0012 0012 0012 0012 0024 0012 0012 0012 0012 0024 0012 0012 0012 0012 0012 0012 0012 0012 0012 0012 0012 0012 0024 0012 0012 0024 0012 0012 0012 106a</ccf>
    </code>
    <code name="KEY_DOWN" codeno="0x000000000000B7F2">
      <ccf>0000 0049 001d 0000 0093 006b 0024 0012 0012 0012 0012 0012 0024 0024 0012 0012 0012 0012 0012 0012 0012 0012 0012 0012 0012 0012 0012 0012 0012 0012 0012 0012 0012 0012 0012 0012 0012 0012 0024 0024 0012 0012 0024 0024 0012 0012 0012 0012 0012 0012 0012 0012 0012 0012 0012 0012 0024 0012 0012 0024 0024 106a</ccf>
    </code>
    <code name="KEY_LEFT" codeno="0x000000000000A7F1">
      <ccf>0000 0049 001e 0000 0093 006b 0024 0012 0012 0012 0012 0012 0024 0024 0012 0012 0012 0012 0012 0012 0012 0012 0012 0012 0012 0012 0012 0012 0012 0012 0012 0012 0012 0012 0012 0012 0012 0012 0024 0024 0024 0012 0012 0024 0012 0012 0012 0012 0012 0012 0012 0012 0012 0012 0012 0012 0024 0012 0012 0012 0012 0024 0012 106a</ccf>
    </code>
    <code name="KEY_RIGHT" codeno="0x00000000000097F0">
      <ccf>0000 0049 001e 0000 0093 006b 0024 0012 0012 0012 0012 0012 0024 0024 0012 0012 0012 0012 0012 0012 0012 0012 0012 0012 0012 0012 0012 0012 0012 0012 0012 0012 0012 0012 0012 0012 0012 0012 0024 0012 0012 0024 0024 0024 0012 0012 0012 0012 0012 0012 0012 0012 0012 0012 0012 0012 0024 0012 0012 0012 0012 0012 0012 106a</ccf>
    </code>
    <code name="KEY_MENU" codeno="0x000000000000B6F1">
      <ccf>0000 0049 001d 0000 0093 006b 0024 0012 0012 0012 0012 0012 0024 0024 0012 0012 0012 0012 0012 0012 0012 0012 0012 0012 0012 0012 0012 0012 0012 0012 0012 0012 0012 0012 0012 0012 0012 0012 0024 0024 0012 0012 0024 0024 0012 0012 0024 0024 0012 0012 0012 0012 0012 0012 0024 0012 0012 0012 0012 0024 0012 106a</ccf>
    </code>
    <code name="KEY_BACK" codeno="0x000000000000A4FE">
      <ccf>0000 0049 001d 0000 0093 006b 0024 0012 0012 0012 0012 0012 0024 0024 0012 0012 0012 0012 0012 0012 0012 0012 0012 0012 0012 0012 0012 0012 0012 0012 0012 0012 0012 0012 0012 0012 0012 0012 0024 0024 0024 0012 0012 0024 0024 0012 0012 0024 0012 0012 0012 0012 0012 0012 0012 0012 0012 0012 0012 0012 0024 106a</ccf>
    </code>
    <code name="KEY_INFO" codeno="0x00000000000083FB">
      <ccf>0000 0049 001f 0000 0093 006b 0024 0012 0012 0012 0012 0012 0024 0024 0012 0012 0012 0012 0012 0012 0012 0012 0012 0012 0012 0012 0012 0012 0012 0012 0012 0012 0012 0012 0012 0012 0012 0012 0024 0012 0012 0012 0012 0012 0012 0012 0012 0024 0012 0012 0012 0012 0012 0012 0012 0012 0012 0012 0012 0012 0024 0024 0012 0012 0012 106a</ccf>
    </code>
    <code name="KEY_STOP" codeno="0x000000000000F2F1">
      <ccf>0000 0049 001e 0000 0093 006b 0024 0012 0012 0012 0012 0012 0024 0024 0012 0012 0012 0012 0012 0012 0012 0012 0012 0012 0012 0012 0012 0012 0012 0012 0012 0012 0012 0012 0012 0012 0012 0012 0012 0012 0012 0012 0012 0012 0024 0012 0012 0024 0024 0024 0012 0012 0012 0012 0012 0012 0024 0012 0012 0012 0012 0024 0012 106a</ccf>
    </code>
    <code name="start/pause" codeno="0x000000000000E5F3">
      <ccf>0000 0049 001e 0000 0093 006b 0024 0012 0012 0012 0012 0012 0024 0024 0012 0012 0012 0012 0012 0012 0012 0012 0012 0012 0012 0012 0012 0012 0012 0012 0012 0012 0012 0012 0012 0012 0012 0012 0012 0012 0012 0012 0024 0012 0012 0024 0024 0024 0012 0012 0012 0012 0012 0012 0012 0012 0024 0012 0012 0024 0012 0012 0012 106a</ccf>
    </code>
    <code name="fb" codeno="0x000000000000D5F2">
      <ccf>0000 0049 001c 0000 0093 006b 0024 0012 0012 0012 0012 0012 0024 0024 0012 0012 0012 0012 0012 0012 0012 0012 0012 0012 0012 0012 0012 0012 0012 0012 0012 0012 0012 0012 0012 0012 0012 0012 0012 0012 0024 0024 0024 0024 0024 0024 0012 0012 0012 0012 0012 0012 0012 0012 0024 0012 0012 0024 0024 106a</ccf>
    </code>
    <code name="KEY_FASTFORWARD" codeno="0x000000000000C5F1">
      <ccf>0000 0049 001e 0000 0093 006b 0024 0012 0012 0012 0012 0012 0024 0024 0012 0012 0012 0012 0012 0012 0012 0012 0012 0012 0012 0012 0012 0012 0012 0012 0012 0012 0012 0012 0012 0012 0012 0012 0012 0012 0024 0012 0012 0012 0012 0024 0024 0024 0012 0012 0012 0012 0012 0012 0012 0012 0024 0012 0012 0012 0012 0024 0012 106a</ccf>
    </code>
    <code name="square" codeno="0x000000000000B5F0">
      <ccf>0000 0049 001d 0000 0093 006b 0024 0012 0012 0012 0012 0012 0024 0024 0012 0012 0012 0012 0012 0012 0012 0012 0012 0012 0012 0012 0012 0012 0012 0012 0012 0012 0012 0012 0012 0012 0012 0012 0024 0024 0012 0012 0024 0024 0024 0024 0012 0012 0012 0012 0012 0012 0012 0012 0024 0012 0012 0012 0012 0012 0012 106a</ccf>
    </code>
    <code name="KEY_RED" codeno="0x000000000000B4FF">
      <ccf>0000 0049 001e 0000 0093 006b 0024 0012 0012 0012 0012 0012 0024 0024 0012 0012 0012 0012 0012 0012 0012 0012 0012 0012 0012 0012 0012 0012 0012 0012 0012 0012 0012 0012 0012 0012 0012 0012 0024 0024 0012 0012 0024 0024 0024 0012 0012 0024 0012 0012 0012 0012 0012 0012 0012 0012 0012 0012 0012 0012 0012 0012 0012 106a</ccf>
    </code>
    <code name="KEY_GREEN" codeno="0x000000000000C0FC">
      <ccf>0000 0049 001f 0000 0093 006b 0024 0012 0012 0012 0012 0012 0024 0024 0012 0012 0012 0012 0012 0012 0012 0012 0012 0012 0012 0012 0012 0012 0012 0012 0012 0012 0012 0012 0012 0012 0012 0012 0012 0012 0024 0012 0012 0012 0012 0012 0012 0012 0012 0012 0012 0024 0012 0012 0012 0012 0012 0012 0012 0012 0012 0012 0024 0012 0012 106a</ccf>
    </code>
    <code name="KEY_YELLOW" codeno="0x00000000000087FF">
      <ccf>0000 0049 0020 0000 0093 006b 0024 0012 0012 0012 0012 0012 0024 0024 0012 0012 0012 0012 0012 0012 0012 0012 0012 0012 0012 0012 0012 0012 0012 0012 0012 0012 0012 0012 0012 0012 0012 0012 0024 0012 0012 0012 0012 0012 0012 0024 0012 0012 0012 0012 0012 0012 0012 0012 0012 0012 0012 0012 0012 0012 0012 0012 0012 0012 0012 0012 0012 106a</ccf>
    </code>
    <code name="KEY_BLUE" codeno="0x000000000000E0FE">
      <ccf>0000 0049 001f 0000 0093 006b 0024 0012 0012 0012 0012 0012 0024 0024 0012 0012 0012 0012 0012 0012 0012 0012 0012 0012 0012 0012 0012 0012 0012 0012 0012 0012 0012 0012 0012 0012 0012 0012 0012 0012 0012 0012 0024 0012 0012 0012 0012 0012 0012 0012 0012 0024 0012 0012 0012 0012 0012 0012 0012 0012 0012 0012 0012 0012 0024 106a</ccf>
    </code>
    <code name="KEY_VOLUMEUP" codeno="0x000000000000B2FD">
      <ccf>0000 0049 001d 0000 0093 006b 0024 0012 0012 0012 0012 0012 0024 0024 0012 0012 0012 0012 0012 0012 0012 0012 0012 0012 0012 0012 0012 0012 0012 0012 0012 0012 0012 0012 0012 0012 0012 0012 0024 0024 0012 0012 0024 0012 0012 0024 0024 0024 0012 0012 0012 0012 0012 0012 0012 0012 0012 0012 0024 0024 0012 106a</ccf>
    </code>
    <code name="KEY_VOLUMEDOWN" codeno="0x000000000000C2FE">
      <ccf>0000 0049 001e 0000 0093 006b 0024 0012 0012 0012 0012 0012 0024 0024 0012 0012 0012 0012 0012 0012 0012 0012 0012 0012 0012 0012 0012 0012 0012 0012 0012 0012 0012 0012 0012 0012 0012 0012 0012 0012 0024 0012 0012 0012 0012 0012 0012 0024 0024 0024 0012 0012 0012 0012 0012 0012 0012 0012 0012 0012 0012 0012 0024 106a</ccf>
    </code>
    <code name="scroll_up" codeno="0x00000000000080F8">
      <ccf>0000 0049 001f 0000 0093 006b 0024 0012 0012 0012 0012 0012 0024 0024 0012 0012 0012 0012 0012 0012 0012 0012 0012 0012 0012 0012 0012 0012 0012 0012 0012 0012 0012 0012 0012 0012 0012 0012 0024 0012 0012 0012 0012 0012 0012 0012 0012 0012 0012 0012 0012 0024 0012 0012 0012 0012 0012 0012 0012 0012 0024 0012 0012 0012 0012 106a</ccf>
    </code>
    <code name="scroll_down" codeno="0x000000000000F6F5">
      <ccf>0000 0049 001d 0000 0093 006b 0024 0012 0012 0012 0012 0012 0024 0024 0012 0012 0012 0012 0012 0012 0012 0012 0012 0012 0012 0012 0012 0012 0012 0012 0012 0012 0012 0012 0012 0012 0012 0012 0012 0012 0012 0012 0012 0012 0024 0024 0012 0012 0024 0024 0012 0012 0012 0012 0012 0012 0024 0024 0024 0024 0012 106a</ccf>
    </code>
    <code name="scroll_left" codeno="0x000000000000D7F4">
      <ccf>0000 0049 001d 0000 0093 006b 0024 0012 0012 0012 0012 0012 0024 0024 0012 0012 0012 0012 0012 0012 0012 0012 0012 0012 0012 0012 0012 0012 0012 0012 0012 0012 0012 0012 0012 0012 0012 0012 0012 0012 0024 0024 0024 0024 0012 0012 0012 0012 0012 0012 0012 0012 0012 0012 0012 0012 0024 0024 0024 0012 0012 106a</ccf>
    </code>
    <code name="scroll_right" codeno="0x000000000000E7F5">
      <ccf>0000 0049 001e 0000 0093 006b 0024 0012 0012 0012 0012 0012 0024 0024 0012 0012 0012 0012 0012 0012 0012 0012 0012 0012 0012 0012 0012 0012 0012 0012 0012 0012 0012 0012 0012 0012 0012 0012 0012 0012 0012 0012 0024 0012 0012 0024 0012 0012 0012 0012 0012 0012 0012 0012 0012 0012 0012 0012 0024 0024 0024 0024 0012 106a</ccf>
    </code>
    <code name="KEY_POWER" codeno="0x000000000000F7F6">
      <ccf>0000 0049 001e 0000 0093 006b 0024 0012 0012 0012 0012 0012 0024 0024 0012 0012 0012 0012 0012 0012 0012 0012 0012 0012 0012 0012 0012 0012 0012 0012 0012 0012 0012 0012 0012 0012 0012 0012 0012 0012 0012 0012 0012 0012 0024 0024 0012 0012 0012 0012 0012 0012 0012 0012 0012 0012 0012 0012 0024 0024 0012 0012 0024 106a</ccf>
    </code>
  </remote>
</lircremotes>
